geopylib/__init__.py
geopylib/geocoor.py
geopycoor-3.0.dist-info/LICENSE
geopycoor-3.0.dist-info/METADATA
geopycoor-3.0.dist-info/WHEEL
geopycoor-3.0.dist-info/top_level.txt
geopycoor-3.0.dist-info/RECORD
