Metadata-Version: 2.1
Name: geopycoor
Version: 3.0
Summary: Pacote para visualizar mapa
Author: R&N
Author-email: crrc1920@gmail.com
Classifier: Programming Language :: Python :: 3
Classifier: License :: OSI Approved :: MIT License
Classifier: Operating System :: OS Independent
Requires-Python: >=3.8
License-File: LICENSE
